intradomain_toolkit/__init__.py
intradomain_toolkit/disambiguation.py
intradomain_toolkit-0.1.0.dist-info/METADATA
intradomain_toolkit-0.1.0.dist-info/WHEEL
intradomain_toolkit-0.1.0.dist-info/top_level.txt
intradomain_toolkit-0.1.0.dist-info/RECORD
