Metadata-Version: 2.1
Name: intradomain-toolkit
Version: 0.1.0
Summary: A Context Disambiguation Package for Natutal Language Documnents (English)
Home-page: https://github.com/ambarish-moharil/intradomain_toolkit
Author: Ambarish Moharil
Author-email: ambarish.m02@gmail.com
License: MIT License
Platform: UNKNOWN
Classifier: Development Status :: 1 - Planning
Classifier: Intended Audience :: Science/Research
Classifier: License :: OSI Approved :: MIT License
Classifier: Operating System :: POSIX :: Linux
Classifier: Programming Language :: Python :: 3.6
Classifier: Programming Language :: Python :: 3.7
Requires-Dist: pandas
Requires-Dist: numpy
Requires-Dist: transformers
Requires-Dist: matplotlib
Requires-Dist: nltk
Requires-Dist: torch
